lib/__init__.py
lib/samanvay.py
Topsis_samanvay_102103315-0.0.1.dist-info/METADATA
Topsis_samanvay_102103315-0.0.1.dist-info/WHEEL
Topsis_samanvay_102103315-0.0.1.dist-info/top_level.txt
Topsis_samanvay_102103315-0.0.1.dist-info/RECORD
